wzqtest/__init__.py
wzqtest/__main__.py
wzqtest/example.py
wzqtest-0.0.1.dist-info/LICENSE
wzqtest-0.0.1.dist-info/METADATA
wzqtest-0.0.1.dist-info/WHEEL
wzqtest-0.0.1.dist-info/entry_points.txt
wzqtest-0.0.1.dist-info/top_level.txt
wzqtest-0.0.1.dist-info/RECORD
