Metadata-Version: 2.1
Name: wzqtest
Version: 0.0.1
Summary: Example Python Package
Home-page: https://editst.com
Author: wzq
Author-email: wangwood817@gmail.com
License: UNKNOWN
Platform: UNKNOWN
Classifier: License :: OSI Approved :: MIT License
Classifier: Programming Language :: Python :: 3.6
Classifier: Programming Language :: Python :: 3.7
Classifier: Programming Language :: Python :: 3.8
Classifier: Programming Language :: Python :: 3.9
Requires-Python: >=3.6.0
License-File: LICENSE
